{"version":1,"resource":"file:///home/dimgerasimou/.local/src/dwmblocks-blocks/src/bluetooth.c","entries":[{"id":"VGQu.c","timestamp":1745261512995},{"id":"fvll.c","timestamp":1745261554276},{"id":"xuPV.c","timestamp":1745261564727},{"id":"FS1X.c","timestamp":1745261648843},{"id":"oFLI.c","timestamp":1745261721145},{"id":"GXwP.c","timestamp":1745261754176},{"id":"KPmZ.c","timestamp":1745261848919},{"id":"TEMm.c","timestamp":1745261982947},{"id":"m58z.c","timestamp":1745262114137},{"id":"z6fL.c","timestamp":1745262154545},{"id":"HwXi.c","timestamp":1745262203440},{"id":"0xY8.c","timestamp":1745264939138},{"id":"AMBw.c","timestamp":1745351055049},{"id":"1VoX.c","timestamp":1745352744830},{"id":"Db0i.c","timestamp":1745354620832},{"id":"HgVR.c","timestamp":1745355192496}]}